<?xml version="1.0" encoding="UTF-8"?>
<scene id="id269551" GSCVersion="0.12.17" PGFVersion="0.21"><layers><layer id="id112326"><actors><actor id="id824843" prototype="id657774"><attributes><point id="position"><real id="x">384.72265625</real><real id="y">565.18359375</real></point></attributes><aspects><graphics><attributes><boolean id="flipHorizontally">false</boolean><boolean id="flipVertically">false</boolean></attributes></graphics></aspects></actor><actor id="id290738" prototype="id657774"><attributes><point id="position"><real id="x">386.30859375</real><real id="y">339.5390625</real></point></attributes><aspects><graphics><attributes><boolean id="flipHorizontally">false</boolean><boolean id="flipVertically">true</boolean></attributes></graphics></aspects></actor><actor id="id800123" prototype="id934607"><attributes><point id="position"><real id="x">367.54296875</real><real id="y">114.03515625</real></point></attributes><aspects/></actor><actor id="id158623" prototype="id515757"><attributes><point id="position"><real id="x">338.44140625</real><real id="y">663.5625</real></point></attributes><aspects/></actor><actor id="id673835" prototype="id515757"><attributes><point id="position"><real id="x">562.56640625</real><real id="y">663.72265625</real></point></attributes><aspects/></actor><actor id="id119526" prototype="id515757"><attributes><point id="position"><real id="x">787.23828125</real><real id="y">665.32421875</real></point></attributes><aspects/></actor><actor id="id128892" prototype="id515757"><attributes><point id="position"><real id="x">113.84765625</real><real id="y">663.609375</real></point></attributes><aspects/></actor><actor id="id269174" prototype="id865053"><attributes><text id="name">TotalDiceRoll</text><point id="position"><real id="x">611</real><real id="y">100.69921875</real></point><image id="image">BlankDice</image></attributes><aspects/><behaviors><behavior id="id523411" class="DisplayTextBehavior" enabled="true"><attributes><text name="Name" id="name">Total Die Roll</text><text name="Bundle Name" id="bundleName">DisplayText.behavior</text><text name="Text" id="text"><expression><reference keypath="game.attributes.id556201"/></expression></text><text name="Font" id="font">American Typewriter</text><real name="Size" id="size">64</real><index name="Alignment" id="alignment">1</index><boolean name="Wrap" id="wrap">false</boolean><color id="color"><real name="Red" id="red">0.90196079015732</real><real name="Green" id="green">0.90196079015732</real><real name="Blue" id="blue">0.90196079015732</real><real name="Alpha" id="alpha">1</real></color><real name="Offsetx" id="offsetx">0</real><real name="Offsety" id="offsety">0</real><index name="Space" id="space">0</index><index name="Direction Space" id="directionSpace">0</index><angle name="Direction" id="direction">0</angle></attributes></behavior></behaviors></actor><actor id="id613065" prototype="id391106"><attributes><point id="position"><real id="x">550</real><real id="y">375</real></point><size id="size"><real id="width">256</real><real id="height">256</real></size></attributes><aspects/></actor><actor id="id258168" prototype="id285139"><attributes><point id="position"><real id="x">-304.17578125</real><real id="y">465.22265625</real></point></attributes><aspects/></actor><actor id="id487131" prototype="id651429"><attributes><text id="name">Pixel Pit Fighter</text><point id="position"><real id="x">380</real><real id="y">960</real></point><size id="size"><real id="width">200</real><real id="height">50</real></size><color id="color"><real id="red">1</real><real id="green">1</real><real id="blue">1</real><real id="alpha">0</real></color></attributes><aspects/><behaviors><behavior id="id903658" class="DisplayTextBehavior" enabled="true"><attributes><text id="name">Display Text</text><text id="bundleName">DisplayText.behavior</text><text id="text"><expression><reference keypath="self.attributes.name"/></expression></text><text id="font">American Typewriter</text><real id="size">60</real><index id="alignment">1</index><boolean id="wrap">false</boolean><color id="color"><real id="red">1</real><real id="green">1</real><real id="blue">1</real><real id="alpha">1</real></color><real id="offsetx">0</real><real id="offsety">0</real><index id="space">0</index><index id="directionSpace">0</index><angle id="direction">0</angle></attributes></behavior></behaviors></actor><actor id="id665254" prototype="id285139"><attributes><point id="position"><real id="x">180</real><real id="y">375</real></point><size id="size"><real id="width">256</real><real id="height">256</real></size></attributes><aspects><graphics><attributes><boolean id="flipHorizontally">false</boolean></attributes></graphics></aspects></actor><actor id="id482566" prototype="id323088"><attributes><text id="name">maingame</text><point id="position"><real id="x">-24.12890625</real><real id="y">1005.01171875</real></point></attributes><aspects/><behaviors><behavior id="id101003" class="ChangeAttributeAction" enabled="true"><attributes><text id="name">Set Scene Name</text><text id="bundleName">ChangeAttribute.behavior</text><text id="targetAttribute">game.attributes.id228573</text><text id="RHS"><expression><reference keypath="self.attributes.name"/></expression></text></attributes></behavior><behavior id="id450993" class="ChangeAttributeAction" enabled="true"><attributes><text id="name">Set Scene Name</text><text id="bundleName">ChangeAttribute.behavior</text><text id="targetAttribute">game.attributes.id163695</text><text id="RHS"><expression><string xml:space="preserve">0</string></expression></text></attributes></behavior><behavior id="id301060" class="ChangeAttributeAction" enabled="true"><attributes><text id="name">Set Scene Name</text><text id="bundleName">ChangeAttribute.behavior</text><text id="targetAttribute">game.attributes.id646870</text><text id="RHS"><expression><string xml:space="preserve">0</string></expression></text></attributes></behavior><behavior id="id235534" class="ChangeAttributeAction" enabled="true"><attributes><text id="name">Set Fight begins to false</text><text id="bundleName">ChangeAttribute.behavior</text><text id="targetAttribute">game.attributes.id571732</text><text id="RHS">0</text></attributes></behavior><behavior id="id744532" class="ChangeAttributeAction" enabled="true"><attributes><text id="name">Set Intial Roll to False </text><text id="bundleName">ChangeAttribute.behavior</text><text id="targetAttribute">game.attributes.id353697</text><text id="RHS">0</text></attributes></behavior><behavior enabled="true" id="id208589" class="RuleBehavior"><attributes><text id="name">Rule</text><text id="bundleName">Rule.behavior</text><real id="compoundConditionKind">0</real></attributes><conditions><condition id="id320093" pluginPredicateTypeIndex="0" eventType="mouse position"><attributes><index id="conditionType">1</index><text id="subjectAttribute">game.attributes.id612964</text></attributes><predicate type="boolean"><attributes><index id="RHS">0</index></attributes></predicate></condition><condition id="id864927" pluginPredicateTypeIndex="0" eventType="mouse position"><attributes><index id="conditionType">1</index><text id="subjectAttribute">game.attributes.id394277</text></attributes><predicate type="boolean"><attributes><index id="RHS">0</index></attributes></predicate></condition></conditions><behaviors><behavior id="id185855" class="SpawnAction" enabled="true"><attributes><text id="name">Spawn End Hero Dice after Hit</text><text id="bundleName">Spawn.behavior</text><text id="prototypeKey">id738498</text><angle id="direction">0</angle><index id="directionSpace">0</index><real id="x">180</real><real id="y">575</real><index id="positionSpace">1</index><index id="layerOrder">2</index></attributes></behavior><behavior id="id841514" class="SpawnAction" enabled="true"><attributes><text id="name">Spawn End Enemy Dice after Hit</text><text id="bundleName">Spawn.behavior</text><text id="prototypeKey">id303146</text><angle id="direction">0</angle><index id="directionSpace">0</index><real id="x">550</real><real id="y">575</real><index id="positionSpace">1</index><index id="layerOrder">2</index></attributes></behavior></behaviors><elseBehaviors/></behavior></behaviors></actor><actor id="id363894" prototype="id445123"><attributes><point id="position"><real id="x">383.94140625</real><real id="y">211.8359375</real></point></attributes><aspects/></actor><actor id="id107337" prototype="id127685"><attributes><point id="position"><real id="x">375.48046875</real><real id="y">843.41015625</real></point><size id="size"><real id="width">128</real><real id="height">128</real></size></attributes><aspects/></actor><actor id="id698138" prototype="id865053"><attributes><point id="position"><real id="x">180</real><real id="y">100</real></point></attributes><aspects/></actor><actor id="id840462" prototype="id865053"><attributes><text id="name">Dice2</text><point id="position"><real id="x">289</real><real id="y">100</real></point></attributes><aspects/><behaviors><behavior enabled="true" id="id774802" class="RuleBehavior"><attributes><text name="Name" id="name">Die #2</text><text name="Bundle Name" id="bundleName">Rule.behavior</text><real name="Compound Condition Kind" id="compoundConditionKind">0</real></attributes><conditions><condition id="id946287" eventType="touch"><attributes><index name="Condition Type" id="conditionType">0</index><attribute name="Subject Attribute" id="subjectAttribute"/></attributes><predicate type="touch" conditionType="pressed"><attributes/></predicate></condition><condition id="id135864" pluginPredicateTypeIndex="0" eventType="mouse position"><attributes><index id="conditionType">1</index><text id="subjectAttribute">game.attributes.id925615</text></attributes><predicate type="boolean"><attributes><index id="RHS">0</index></attributes></predicate></condition><condition id="id308757" pluginPredicateTypeIndex="0" eventType="mouse position"><attributes><index id="conditionType">1</index><text id="subjectAttribute">game.attributes.id646870</text></attributes><predicate type="boolean"><attributes><index id="RHS">1</index></attributes></predicate></condition></conditions><behaviors><behavior id="id738116" class="CompoundBehavior" enabled="true"><attributes><text id="name">Shrink and Grow Dice</text><text id="bundleName">Group.behavior</text></attributes><behaviors><behavior id="id604403" class="ChangeAttributeAction" enabled="true"><attributes><text id="name">Change Attribute</text><text id="bundleName">ChangeAttribute.behavior</text><text id="targetAttribute">self.attributes.color.alpha</text><text id="RHS">0</text></attributes></behavior><behavior id="id506167" class="InterpolateBehavior" enabled="true"><attributes><text id="name">Interpolate</text><text id="bundleName">Interpolate.behavior</text><boolean id="runToCompletion">true</boolean><text id="targetAttribute">self.attributes.color.alpha</text><real id="finalValue">1</real><real id="duration">0.3</real><index id="easing">1</index></attributes></behavior><behavior id="id953526" class="ChangeAttributeAction" enabled="true"><attributes><text id="name">Change Attribute</text><text id="bundleName">ChangeAttribute.behavior</text><text id="targetAttribute">self.attributes.size.width</text><text id="RHS">200</text></attributes></behavior><behavior id="id215689" class="ChangeAttributeAction" enabled="true"><attributes><text id="name">Change Attribute</text><text id="bundleName">ChangeAttribute.behavior</text><text id="targetAttribute">self.attributes.size.height</text><text id="RHS">200</text></attributes></behavior><behavior id="id494093" class="InterpolateBehavior" enabled="true"><attributes><text id="name">Interpolate</text><text id="bundleName">Interpolate.behavior</text><boolean id="runToCompletion">true</boolean><text id="targetAttribute">self.attributes.size.width</text><real id="finalValue">100</real><real id="duration">0.5</real><index id="easing">0</index></attributes></behavior><behavior id="id528887" class="InterpolateBehavior" enabled="true"><attributes><text id="name">Interpolate</text><text id="bundleName">Interpolate.behavior</text><boolean id="runToCompletion">true</boolean><text id="targetAttribute">self.attributes.size.height</text><real id="finalValue">100</real><real id="duration">0.5</real><index id="easing">0</index></attributes></behavior></behaviors></behavior><behavior id="id200642" class="PlaySoundAction" enabled="true"><attributes><text name="Name" id="name">Play DICE Sound</text><text name="Bundle Name" id="bundleName">PlaySound.behavior</text><sound name="Sound Name" id="soundName">Dice</sound><boolean name="Loop" id="loop">false</boolean><boolean name="Run To Completion" id="runToCompletion">true</boolean><boolean name="Positional" id="positional">false</boolean><boolean name="Doppler Shift" id="dopplerShift">false</boolean><real name="Volume" id="volume">1</real><real name="Pitch" id="pitch">1</real></attributes></behavior><behavior id="id475079" class="ChangeAttributeAction" enabled="true"><attributes><text name="Name" id="name">Randomize Dice</text><text name="Bundle Name" id="bundleName">ChangeAttribute.behavior</text><text name="Target Attribute" id="targetAttribute">game.attributes.id179225</text><text name="RHS" id="RHS"><expression><string xml:space="preserve">random(1,6)</string></expression></text></attributes></behavior><behavior id="id363239" class="ChangeAttributeAction" enabled="true"><attributes><text name="Name" id="name">Change the image</text><text name="Bundle Name" id="bundleName">ChangeAttribute.behavior</text><text name="Target Attribute" id="targetAttribute">self.attributes.image</text><text name="RHS" id="RHS"><expression><string xml:space="preserve">&quot;D&quot;..</string><reference keypath="game.attributes.id179225"/><string xml:space="preserve">..&quot;.png&quot;</string></expression></text></attributes></behavior><behavior id="id964524" class="ChangeAttributeAction" enabled="true"><attributes><text name="Name" id="name">Change D2 rolled to True</text><text name="Bundle Name" id="bundleName">ChangeAttribute.behavior</text><text name="Target Attribute" id="targetAttribute">game.attributes.id925615</text><text name="RHS" id="RHS">1</text></attributes></behavior></behaviors><elseBehaviors><behavior enabled="true" id="id513356" class="RuleBehavior"><attributes><text name="Name" id="name">Rule</text><text name="Bundle Name" id="bundleName">Rule.behavior</text><real name="Compound Condition Kind" id="compoundConditionKind">0</real></attributes><conditions><condition id="id640710" eventType="mouse position"><attributes><index name="Condition Type" id="conditionType">1</index><text name="Subject Attribute" id="subjectAttribute">game.attributes.id925615</text></attributes><predicate type="boolean"><attributes><index id="RHS">0</index></attributes></predicate></condition></conditions><behaviors><behavior id="id275631" class="TimerBehavior" enabled="true"><attributes><text name="Name" id="name">Timer</text><text name="Bundle Name" id="bundleName">Timer.behavior</text><index name="Timer Type" id="timerType">0</index><real name="Interval" id="interval">0.1</real><boolean name="Run To Completion" id="runToCompletion">true</boolean></attributes><behaviors><behavior id="id498002" class="ChangeAttributeAction" enabled="true"><attributes><text name="Name" id="name">Change image to Dice Roll</text><text name="Bundle Name" id="bundleName">ChangeAttribute.behavior</text><text name="Target Attribute" id="targetAttribute">self.attributes.image</text><text name="RHS" id="RHS"><expression><string xml:space="preserve">&quot;D&quot;..random(1,6)..&quot;.png&quot;</string></expression></text></attributes></behavior></behaviors></behavior></behaviors><elseBehaviors/></behavior></elseBehaviors></behavior><behavior enabled="true" id="id824328" class="RuleBehavior"><attributes><text name="Name" id="name">Enemy Die #2</text><text name="Bundle Name" id="bundleName">Rule.behavior</text><real name="Compound Condition Kind" id="compoundConditionKind">0</real></attributes><conditions><condition id="id135864" pluginPredicateTypeIndex="0" eventType="mouse position"><attributes><index id="conditionType">1</index><text id="subjectAttribute">game.attributes.id925615</text></attributes><predicate type="boolean"><attributes><index id="RHS">0</index></attributes></predicate></condition><condition id="id878941" pluginPredicateTypeIndex="0" eventType="mouse position"><attributes><index id="conditionType">1</index><text id="subjectAttribute">game.attributes.id163695</text></attributes><predicate type="boolean"><attributes><index id="RHS">1</index></attributes></predicate></condition></conditions><behaviors><behavior id="id200642" class="PlaySoundAction" enabled="true"><attributes><text name="Name" id="name">Play Sound</text><text name="Bundle Name" id="bundleName">PlaySound.behavior</text><sound name="Sound Name" id="soundName">Dice</sound><boolean name="Loop" id="loop">false</boolean><boolean name="Run To Completion" id="runToCompletion">true</boolean><boolean name="Positional" id="positional">false</boolean><boolean name="Doppler Shift" id="dopplerShift">false</boolean><real name="Volume" id="volume">1</real><real name="Pitch" id="pitch">1</real></attributes></behavior><behavior id="id475079" class="ChangeAttributeAction" enabled="true"><attributes><text name="Name" id="name">Roll Dice 3</text><text name="Bundle Name" id="bundleName">ChangeAttribute.behavior</text><text name="Target Attribute" id="targetAttribute">game.attributes.id179225</text><text name="RHS" id="RHS"><expression><string xml:space="preserve">random(1,6)</string></expression></text></attributes></behavior><behavior id="id363239" class="ChangeAttributeAction" enabled="true"><attributes><text name="Name" id="name">Change Dice Image</text><text name="Bundle Name" id="bundleName">ChangeAttribute.behavior</text><text name="Target Attribute" id="targetAttribute">self.attributes.image</text><text name="RHS" id="RHS"><expression><string xml:space="preserve">&quot;D&quot;..</string><reference keypath="game.attributes.id179225"/><string xml:space="preserve">..&quot;.png&quot;</string></expression></text></attributes></behavior><behavior id="id964524" class="ChangeAttributeAction" enabled="true"><attributes><text name="Name" id="name">Set Dice #2 rolled to true</text><text name="Bundle Name" id="bundleName">ChangeAttribute.behavior</text><text name="Target Attribute" id="targetAttribute">game.attributes.id925615</text><text name="RHS" id="RHS">1</text></attributes></behavior></behaviors><elseBehaviors><behavior enabled="true" id="id513356" class="RuleBehavior"><attributes><text name="Name" id="name">Randommize Dice Image</text><text name="Bundle Name" id="bundleName">Rule.behavior</text><real name="Compound Condition Kind" id="compoundConditionKind">0</real></attributes><conditions><condition id="id640710" eventType="mouse position"><attributes><index name="Condition Type" id="conditionType">1</index><text name="Subject Attribute" id="subjectAttribute">game.attributes.id925615</text></attributes><predicate type="boolean"><attributes><index id="RHS">0</index></attributes></predicate></condition></conditions><behaviors><behavior id="id275631" class="TimerBehavior" enabled="true"><attributes><text name="Name" id="name">Timer</text><text name="Bundle Name" id="bundleName">Timer.behavior</text><index name="Timer Type" id="timerType">0</index><real name="Interval" id="interval">0.1</real><boolean name="Run To Completion" id="runToCompletion">true</boolean></attributes><behaviors><behavior id="id498002" class="ChangeAttributeAction" enabled="true"><attributes><text name="Name" id="name">Change image to Dice Roll</text><text name="Bundle Name" id="bundleName">ChangeAttribute.behavior</text><text name="Target Attribute" id="targetAttribute">self.attributes.image</text><text name="RHS" id="RHS"><expression><string xml:space="preserve">&quot;D&quot;..random(1,6)..&quot;.png&quot;</string></expression></text></attributes></behavior></behaviors></behavior></behaviors><elseBehaviors/></behavior></elseBehaviors></behavior></behaviors></actor><actor id="id495850" prototype="id865053"><attributes><text id="name">Dice3</text><point id="position"><real id="x">398</real><real id="y">101.04296875</real></point></attributes><aspects/><behaviors><behavior enabled="true" id="id527811" class="RuleBehavior"><attributes><text name="Name" id="name">Hero Die #3 and Hit &amp; Miss</text><text name="Bundle Name" id="bundleName">Rule.behavior</text><real name="Compound Condition Kind" id="compoundConditionKind">0</real></attributes><conditions><condition id="id946287" eventType="touch"><attributes><index name="Condition Type" id="conditionType">0</index><attribute name="Subject Attribute" id="subjectAttribute"/></attributes><predicate type="touch" conditionType="pressed"><attributes/></predicate></condition><condition id="id135864" pluginPredicateTypeIndex="0" eventType="mouse position"><attributes><index id="conditionType">1</index><text id="subjectAttribute">game.attributes.id911334</text></attributes><predicate type="boolean"><attributes><index id="RHS">0</index></attributes></predicate></condition><condition id="id470109" pluginPredicateTypeIndex="0" eventType="mouse position"><attributes><index id="conditionType">1</index><text id="subjectAttribute">game.attributes.id646870</text></attributes><predicate type="boolean"><attributes><index id="RHS">1</index></attributes></predicate></condition></conditions><behaviors><behavior id="id527655" class="CompoundBehavior" enabled="true"><attributes><text id="name">Shrink and Grow Dice</text><text id="bundleName">Group.behavior</text></attributes><behaviors><behavior id="id604403" class="ChangeAttributeAction" enabled="true"><attributes><text id="name">Change Attribute</text><text id="bundleName">ChangeAttribute.behavior</text><text id="targetAttribute">self.attributes.color.alpha</text><text id="RHS">0</text></attributes></behavior><behavior id="id506167" class="InterpolateBehavior" enabled="true"><attributes><text id="name">Interpolate</text><text id="bundleName">Interpolate.behavior</text><boolean id="runToCompletion">true</boolean><text id="targetAttribute">self.attributes.color.alpha</text><real id="finalValue">1</real><real id="duration">0.3</real><index id="easing">1</index></attributes></behavior><behavior id="id953526" class="ChangeAttributeAction" enabled="true"><attributes><text id="name">Change Attribute</text><text id="bundleName">ChangeAttribute.behavior</text><text id="targetAttribute">self.attributes.size.width</text><text id="RHS">200</text></attributes></behavior><behavior id="id215689" class="ChangeAttributeAction" enabled="true"><attributes><text id="name">Change Attribute</text><text id="bundleName">ChangeAttribute.behavior</text><text id="targetAttribute">self.attributes.size.height</text><text id="RHS">200</text></attributes></behavior><behavior id="id494093" class="InterpolateBehavior" enabled="true"><attributes><text id="name">Interpolate</text><text id="bundleName">Interpolate.behavior</text><boolean id="runToCompletion">true</boolean><text id="targetAttribute">self.attributes.size.width</text><real id="finalValue">100</real><real id="duration">0.5</real><index id="easing">0</index></attributes></behavior><behavior id="id528887" class="InterpolateBehavior" enabled="true"><attributes><text id="name">Interpolate</text><text id="bundleName">Interpolate.behavior</text><boolean id="runToCompletion">true</boolean><text id="targetAttribute">self.attributes.size.height</text><real id="finalValue">100</real><real id="duration">0.5</real><index id="easing">0</index></attributes></behavior></behaviors></behavior><behavior id="id200642" class="PlaySoundAction" enabled="true"><attributes><text name="Name" id="name">Play Sound</text><text name="Bundle Name" id="bundleName">PlaySound.behavior</text><sound name="Sound Name" id="soundName">Dice</sound><boolean name="Loop" id="loop">false</boolean><boolean name="Run To Completion" id="runToCompletion">true</boolean><boolean name="Positional" id="positional">false</boolean><boolean name="Doppler Shift" id="dopplerShift">false</boolean><real name="Volume" id="volume">1</real><real name="Pitch" id="pitch">1</real></attributes></behavior><behavior id="id475079" class="ChangeAttributeAction" enabled="true"><attributes><text name="Name" id="name">Roll Dice 3</text><text name="Bundle Name" id="bundleName">ChangeAttribute.behavior</text><text name="Target Attribute" id="targetAttribute">game.attributes.id545723</text><text name="RHS" id="RHS"><expression><string xml:space="preserve">random(1,6)</string></expression></text></attributes></behavior><behavior id="id363239" class="ChangeAttributeAction" enabled="true"><attributes><text name="Name" id="name">Change Dice Image</text><text name="Bundle Name" id="bundleName">ChangeAttribute.behavior</text><text name="Target Attribute" id="targetAttribute">self.attributes.image</text><text name="RHS" id="RHS"><expression><string xml:space="preserve">&quot;D&quot;..</string><reference keypath="game.attributes.id545723"/><string xml:space="preserve">..&quot;.png&quot;</string></expression></text></attributes></behavior><behavior id="id964524" class="ChangeAttributeAction" enabled="true"><attributes><text name="Name" id="name">Set Dice #3 rolled to true</text><text name="Bundle Name" id="bundleName">ChangeAttribute.behavior</text><text name="Target Attribute" id="targetAttribute">game.attributes.id911334</text><text name="RHS" id="RHS">1</text></attributes></behavior><behavior id="id388115" class="ChangeAttributeAction" enabled="true"><attributes><text name="Name" id="name">Total Dice Roll</text><text name="Bundle Name" id="bundleName">ChangeAttribute.behavior</text><text name="Target Attribute" id="targetAttribute">game.attributes.id556201</text><text name="RHS" id="RHS"><expression><string xml:space="preserve">(</string><reference keypath="game.attributes.id663716"/><string xml:space="preserve">+</string><reference keypath="game.attributes.id179225"/><string xml:space="preserve">+</string><reference keypath="game.attributes.id545723"/><string xml:space="preserve">)</string></expression></text></attributes></behavior><behavior id="id716193" class="ChangeAttributeAction" enabled="true"><attributes><text name="Name" id="name">Add Dex Penality</text><text name="Bundle Name" id="bundleName">ChangeAttribute.behavior</text><text name="Target Attribute" id="targetAttribute">game.attributes.id556201</text><text name="RHS" id="RHS"><expression><reference keypath="game.attributes.id556201"/><string xml:space="preserve">+</string><reference keypath="game.attributes.id683141"/></expression></text></attributes></behavior><behavior id="id364503" class="ChangeAttributeAction" enabled="true"><attributes><text id="name">Attack Dice Rolled</text><text id="bundleName">ChangeAttribute.behavior</text><text id="targetAttribute">game.attributes.id632683</text><text id="RHS">1</text></attributes></behavior><behavior enabled="true" id="id902264" class="RuleBehavior"><attributes><text id="name">Hero Win Hit </text><text id="bundleName">Rule.behavior</text><real id="compoundConditionKind">0</real></attributes><conditions><condition id="id233627" pluginPredicateTypeIndex="0" eventType="mouse position"><attributes><index id="conditionType">1</index><text id="subjectAttribute">game.attributes.id556201</text></attributes><predicate type="number"><attributes><text id="operator">&lt;=</text><real id="RHS"><expression><reference keypath="game.attributes.id891234"/></expression></real></attributes></predicate></condition></conditions><behaviors><behavior id="id128807" class="ChangeAttributeAction" enabled="false"><attributes><text id="name">Change Hero Attack to True</text><text id="bundleName">ChangeAttribute.behavior</text><text id="targetAttribute">game.attributes.id646870</text><text id="RHS">1</text></attributes></behavior><behavior id="id793958" class="CompoundBehavior" enabled="true"><attributes><text id="name">Spawn H I T</text><text id="bundleName">Group.behavior</text></attributes><behaviors><behavior id="id366015" class="SpawnAction" enabled="true"><attributes><text id="name">Spawn Actor</text><text id="bundleName">Spawn.behavior</text><text id="prototypeKey">id401385</text><angle id="direction">0</angle><index id="directionSpace">0</index><real id="x">310</real><real id="y">575</real><index id="positionSpace">1</index><index id="layerOrder">2</index></attributes></behavior><behavior id="id727018" class="SpawnAction" enabled="true"><attributes><text id="name">Spawn Actor</text><text id="bundleName">Spawn.behavior</text><text id="prototypeKey">id672850</text><angle id="direction">0</angle><index id="directionSpace">0</index><real id="x">385</real><real id="y">575</real><index id="positionSpace">1</index><index id="layerOrder">2</index></attributes></behavior><behavior id="id292626" class="SpawnAction" enabled="true"><attributes><text id="name">Spawn Actor</text><text id="bundleName">Spawn.behavior</text><text id="prototypeKey">id410438</text><angle id="direction">0</angle><index id="directionSpace">0</index><real id="x">450</real><real id="y">575</real><index id="positionSpace">1</index><index id="layerOrder">2</index></attributes></behavior><behavior id="id282165" class="PlaySoundAction" enabled="true"><attributes><text id="name">Play Sound</text><text id="bundleName">PlaySound.behavior</text><sound id="soundName">Swords</sound><boolean id="loop">false</boolean><boolean id="runToCompletion">true</boolean><boolean id="positional">false</boolean><boolean id="dopplerShift">false</boolean><real id="volume">1</real><real id="pitch">1</real></attributes></behavior><behavior id="id357915" class="SpawnAction" enabled="true"><attributes><text id="name">Spawn End Hero Dice after Hit</text><text id="bundleName">Spawn.behavior</text><text id="prototypeKey">id738498</text><angle id="direction">0</angle><index id="directionSpace">0</index><real id="x">180</real><real id="y">575</real><index id="positionSpace">1</index><index id="layerOrder">2</index></attributes></behavior></behaviors></behavior></behaviors><elseBehaviors><behavior id="id687856" class="CompoundBehavior" enabled="true"><attributes><text id="name">Spell out  M I S S</text><text id="bundleName">Group.behavior</text></attributes><behaviors><behavior id="id366015" class="SpawnAction" enabled="true"><attributes><text id="name">Spawn Actor</text><text id="bundleName">Spawn.behavior</text><text id="prototypeKey">id688254</text><angle id="direction">0</angle><index id="directionSpace">0</index><real id="x">310</real><real id="y">575</real><index id="positionSpace">1</index><index id="layerOrder">2</index></attributes></behavior><behavior id="id727018" class="SpawnAction" enabled="true"><attributes><text id="name">Spawn Actor</text><text id="bundleName">Spawn.behavior</text><text id="prototypeKey">id672850</text><angle id="direction">0</angle><index id="directionSpace">0</index><real id="x">385</real><real id="y">575</real><index id="positionSpace">1</index><index id="layerOrder">2</index></attributes></behavior><behavior id="id323975" class="SpawnAction" enabled="true"><attributes><text id="name">Spawn Actor</text><text id="bundleName">Spawn.behavior</text><text id="prototypeKey">id305553</text><angle id="direction">0</angle><index id="directionSpace">0</index><real id="x">450</real><real id="y">575</real><index id="positionSpace">1</index><index id="layerOrder">2</index></attributes></behavior><behavior id="id292626" class="SpawnAction" enabled="true"><attributes><text id="name">Spawn Actor</text><text id="bundleName">Spawn.behavior</text><text id="prototypeKey">id305553</text><angle id="direction">0</angle><index id="directionSpace">0</index><real id="x">525</real><real id="y">575</real><index id="positionSpace">1</index><index id="layerOrder">2</index></attributes></behavior><behavior id="id898441" class="TimerBehavior" enabled="true"><attributes><text id="name">Spawn End Hero Turn after Miss</text><text id="bundleName">Timer.behavior</text><index id="timerType">1</index><real id="interval">1</real><boolean id="runToCompletion">true</boolean></attributes><behaviors><behavior id="id932196" class="SpawnAction" enabled="true"><attributes><text id="name">Spawn Actor</text><text id="bundleName">Spawn.behavior</text><text id="prototypeKey">id388855</text><angle id="direction">0</angle><index id="directionSpace">0</index><real id="x">380</real><real id="y">200</real><index id="positionSpace">1</index><index id="layerOrder">0</index></attributes></behavior></behaviors></behavior></behaviors></behavior></elseBehaviors></behavior></behaviors><elseBehaviors><behavior enabled="true" id="id513356" class="RuleBehavior"><attributes><text name="Name" id="name">Randommize Dice Image</text><text name="Bundle Name" id="bundleName">Rule.behavior</text><real name="Compound Condition Kind" id="compoundConditionKind">0</real></attributes><conditions><condition id="id640710" eventType="mouse position"><attributes><index name="Condition Type" id="conditionType">1</index><text name="Subject Attribute" id="subjectAttribute">game.attributes.id911334</text></attributes><predicate type="boolean"><attributes><index id="RHS">0</index></attributes></predicate></condition></conditions><behaviors><behavior id="id275631" class="TimerBehavior" enabled="true"><attributes><text name="Name" id="name">Timer</text><text name="Bundle Name" id="bundleName">Timer.behavior</text><index name="Timer Type" id="timerType">0</index><real name="Interval" id="interval">0.1</real><boolean name="Run To Completion" id="runToCompletion">true</boolean></attributes><behaviors><behavior id="id498002" class="ChangeAttributeAction" enabled="true"><attributes><text name="Name" id="name">Change image to Dice Roll</text><text name="Bundle Name" id="bundleName">ChangeAttribute.behavior</text><text name="Target Attribute" id="targetAttribute">self.attributes.image</text><text name="RHS" id="RHS"><expression><string xml:space="preserve">&quot;D&quot;..random(1,6)..&quot;.png&quot;</string></expression></text></attributes></behavior></behaviors></behavior></behaviors><elseBehaviors/></behavior></elseBehaviors></behavior><behavior enabled="true" id="id644825" class="RuleBehavior"><attributes><text name="Name" id="name">Enemy Die #3 and Hit &amp; Miss</text><text name="Bundle Name" id="bundleName">Rule.behavior</text><real name="Compound Condition Kind" id="compoundConditionKind">0</real></attributes><conditions><condition id="id135864" pluginPredicateTypeIndex="0" eventType="mouse position"><attributes><index id="conditionType">1</index><text id="subjectAttribute">game.attributes.id911334</text></attributes><predicate type="boolean"><attributes><index id="RHS">0</index></attributes></predicate></condition><condition id="id878941" pluginPredicateTypeIndex="0" eventType="mouse position"><attributes><index id="conditionType">1</index><text id="subjectAttribute">game.attributes.id163695</text></attributes><predicate type="boolean"><attributes><index id="RHS">1</index></attributes></predicate></condition></conditions><behaviors><behavior id="id200642" class="PlaySoundAction" enabled="true"><attributes><text name="Name" id="name">Play Sound</text><text name="Bundle Name" id="bundleName">PlaySound.behavior</text><sound name="Sound Name" id="soundName">Dice</sound><boolean name="Loop" id="loop">false</boolean><boolean name="Run To Completion" id="runToCompletion">true</boolean><boolean name="Positional" id="positional">false</boolean><boolean name="Doppler Shift" id="dopplerShift">false</boolean><real name="Volume" id="volume">1</real><real name="Pitch" id="pitch">1</real></attributes></behavior><behavior id="id475079" class="ChangeAttributeAction" enabled="true"><attributes><text name="Name" id="name">Roll Dice 3</text><text name="Bundle Name" id="bundleName">ChangeAttribute.behavior</text><text name="Target Attribute" id="targetAttribute">game.attributes.id545723</text><text name="RHS" id="RHS"><expression><string xml:space="preserve">random(1,6)</string></expression></text></attributes></behavior><behavior id="id363239" class="ChangeAttributeAction" enabled="true"><attributes><text name="Name" id="name">Change Dice Image</text><text name="Bundle Name" id="bundleName">ChangeAttribute.behavior</text><text name="Target Attribute" id="targetAttribute">self.attributes.image</text><text name="RHS" id="RHS"><expression><string xml:space="preserve">&quot;D&quot;..</string><reference keypath="game.attributes.id545723"/><string xml:space="preserve">..&quot;.png&quot;</string></expression></text></attributes></behavior><behavior id="id964524" class="ChangeAttributeAction" enabled="true"><attributes><text name="Name" id="name">Set Dice #3 rolled to true</text><text name="Bundle Name" id="bundleName">ChangeAttribute.behavior</text><text name="Target Attribute" id="targetAttribute">game.attributes.id911334</text><text name="RHS" id="RHS">1</text></attributes></behavior><behavior id="id690145" class="ChangeAttributeAction" enabled="true"><attributes><text id="name">Set Dice Roll to True</text><text id="bundleName">ChangeAttribute.behavior</text><text id="targetAttribute">game.attributes.id960311</text><text id="RHS">1</text></attributes></behavior><behavior id="id388115" class="ChangeAttributeAction" enabled="true"><attributes><text name="Name" id="name">Total Dice Roll</text><text name="Bundle Name" id="bundleName">ChangeAttribute.behavior</text><text name="Target Attribute" id="targetAttribute">game.attributes.id556201</text><text name="RHS" id="RHS"><expression><string xml:space="preserve">(</string><reference keypath="game.attributes.id663716"/><string xml:space="preserve">+</string><reference keypath="game.attributes.id179225"/><string xml:space="preserve">+</string><reference keypath="game.attributes.id545723"/><string xml:space="preserve">)</string></expression></text></attributes></behavior><behavior id="id716193" class="ChangeAttributeAction" enabled="true"><attributes><text name="Name" id="name">Add Dex Penality</text><text name="Bundle Name" id="bundleName">ChangeAttribute.behavior</text><text name="Target Attribute" id="targetAttribute">game.attributes.id556201</text><text name="RHS" id="RHS"><expression><reference keypath="game.attributes.id556201"/><string xml:space="preserve">+</string><reference keypath="game.attributes.id298165"/></expression></text></attributes></behavior><behavior enabled="true" id="id902264" class="RuleBehavior"><attributes><text id="name">Enemy Hit </text><text id="bundleName">Rule.behavior</text><real id="compoundConditionKind">0</real></attributes><conditions><condition id="id233627" pluginPredicateTypeIndex="0" eventType="mouse position"><attributes><index id="conditionType">1</index><text id="subjectAttribute">game.attributes.id556201</text></attributes><predicate type="number"><attributes><text id="operator">&lt;=</text><real id="RHS"><expression><reference keypath="game.attributes.id891234"/></expression></real></attributes></predicate></condition></conditions><behaviors><behavior id="id128807" class="ChangeAttributeAction" enabled="true"><attributes><text id="name">Change Enemy Attack to True</text><text id="bundleName">ChangeAttribute.behavior</text><text id="targetAttribute">game.attributes.id163695</text><text id="RHS">1</text></attributes></behavior><behavior id="id793958" class="CompoundBehavior" enabled="true"><attributes><text id="name">Spawn H I T</text><text id="bundleName">Group.behavior</text></attributes><behaviors><behavior id="id366015" class="SpawnAction" enabled="true"><attributes><text id="name">Spawn Actor</text><text id="bundleName">Spawn.behavior</text><text id="prototypeKey">id401385</text><angle id="direction">0</angle><index id="directionSpace">0</index><real id="x">310</real><real id="y">575</real><index id="positionSpace">1</index><index id="layerOrder">2</index></attributes></behavior><behavior id="id727018" class="SpawnAction" enabled="true"><attributes><text id="name">Spawn Actor</text><text id="bundleName">Spawn.behavior</text><text id="prototypeKey">id672850</text><angle id="direction">0</angle><index id="directionSpace">0</index><real id="x">385</real><real id="y">575</real><index id="positionSpace">1</index><index id="layerOrder">2</index></attributes></behavior><behavior id="id292626" class="SpawnAction" enabled="true"><attributes><text id="name">Spawn Actor</text><text id="bundleName">Spawn.behavior</text><text id="prototypeKey">id410438</text><angle id="direction">0</angle><index id="directionSpace">0</index><real id="x">450</real><real id="y">575</real><index id="positionSpace">1</index><index id="layerOrder">2</index></attributes></behavior><behavior id="id282165" class="PlaySoundAction" enabled="true"><attributes><text id="name">Play Sound</text><text id="bundleName">PlaySound.behavior</text><sound id="soundName">Swords</sound><boolean id="loop">false</boolean><boolean id="runToCompletion">true</boolean><boolean id="positional">false</boolean><boolean id="dopplerShift">false</boolean><real id="volume">1</real><real id="pitch">1</real></attributes></behavior><behavior id="id357915" class="SpawnAction" enabled="true"><attributes><text id="name">Spawn End Enemy Dice after Hit</text><text id="bundleName">Spawn.behavior</text><text id="prototypeKey">id303146</text><angle id="direction">0</angle><index id="directionSpace">0</index><real id="x">550</real><real id="y">575</real><index id="positionSpace">1</index><index id="layerOrder">2</index></attributes></behavior></behaviors></behavior></behaviors><elseBehaviors><behavior id="id404332" class="ChangeAttributeAction" enabled="true"><attributes><text id="name">Change Enemy Attack to True</text><text id="bundleName">ChangeAttribute.behavior</text><text id="targetAttribute">game.attributes.id163695</text><text id="RHS">1</text></attributes></behavior><behavior id="id687856" class="CompoundBehavior" enabled="true"><attributes><text id="name">Spell out  M I S S</text><text id="bundleName">Group.behavior</text></attributes><behaviors><behavior id="id366015" class="SpawnAction" enabled="true"><attributes><text id="name">Spawn Actor</text><text id="bundleName">Spawn.behavior</text><text id="prototypeKey">id688254</text><angle id="direction">0</angle><index id="directionSpace">0</index><real id="x">310</real><real id="y">575</real><index id="positionSpace">1</index><index id="layerOrder">2</index></attributes></behavior><behavior id="id727018" class="SpawnAction" enabled="true"><attributes><text id="name">Spawn Actor</text><text id="bundleName">Spawn.behavior</text><text id="prototypeKey">id672850</text><angle id="direction">0</angle><index id="directionSpace">0</index><real id="x">385</real><real id="y">575</real><index id="positionSpace">1</index><index id="layerOrder">2</index></attributes></behavior><behavior id="id323975" class="SpawnAction" enabled="true"><attributes><text id="name">Spawn Actor</text><text id="bundleName">Spawn.behavior</text><text id="prototypeKey">id305553</text><angle id="direction">0</angle><index id="directionSpace">0</index><real id="x">450</real><real id="y">575</real><index id="positionSpace">1</index><index id="layerOrder">2</index></attributes></behavior><behavior id="id292626" class="SpawnAction" enabled="true"><attributes><text id="name">Spawn Actor</text><text id="bundleName">Spawn.behavior</text><text id="prototypeKey">id305553</text><angle id="direction">0</angle><index id="directionSpace">0</index><real id="x">525</real><real id="y">575</real><index id="positionSpace">1</index><index id="layerOrder">2</index></attributes></behavior><behavior id="id898441" class="TimerBehavior" enabled="true"><attributes><text id="name">Spawn End Hero Turn after Miss</text><text id="bundleName">Timer.behavior</text><index id="timerType">1</index><real id="interval">1</real><boolean id="runToCompletion">true</boolean></attributes><behaviors><behavior id="id932196" class="SpawnAction" enabled="true"><attributes><text id="name">Spawn Actor</text><text id="bundleName">Spawn.behavior</text><text id="prototypeKey">id554979</text><angle id="direction">0</angle><index id="directionSpace">0</index><real id="x">380</real><real id="y">200</real><index id="positionSpace">1</index><index id="layerOrder">0</index></attributes></behavior></behaviors></behavior></behaviors></behavior></elseBehaviors></behavior></behaviors><elseBehaviors><behavior enabled="true" id="id513356" class="RuleBehavior"><attributes><text name="Name" id="name">Randommize Dice Image</text><text name="Bundle Name" id="bundleName">Rule.behavior</text><real name="Compound Condition Kind" id="compoundConditionKind">0</real></attributes><conditions><condition id="id640710" eventType="mouse position"><attributes><index name="Condition Type" id="conditionType">1</index><text name="Subject Attribute" id="subjectAttribute">game.attributes.id911334</text></attributes><predicate type="boolean"><attributes><index id="RHS">0</index></attributes></predicate></condition></conditions><behaviors><behavior id="id275631" class="TimerBehavior" enabled="true"><attributes><text name="Name" id="name">Timer</text><text name="Bundle Name" id="bundleName">Timer.behavior</text><index name="Timer Type" id="timerType">0</index><real name="Interval" id="interval">0.1</real><boolean name="Run To Completion" id="runToCompletion">true</boolean></attributes><behaviors><behavior id="id498002" class="ChangeAttributeAction" enabled="true"><attributes><text name="Name" id="name">Change image to Dice Roll</text><text name="Bundle Name" id="bundleName">ChangeAttribute.behavior</text><text name="Target Attribute" id="targetAttribute">self.attributes.image</text><text name="RHS" id="RHS"><expression><string xml:space="preserve">&quot;D&quot;..random(1,6)..&quot;.png&quot;</string></expression></text></attributes></behavior></behaviors></behavior></behaviors><elseBehaviors/></behavior></elseBehaviors></behavior></behaviors></actor><actor id="id139716" prototype="id870832"><attributes><point id="position"><real id="x">505.203125</real><real id="y">99.4140625</real></point></attributes><aspects/></actor><actor id="id281886" prototype="id445123"><attributes><text id="name">EnemyAttack</text><point id="position"><real id="x">573.8828125</real><real id="y">922.0390625</real></point></attributes><aspects/><behaviors><behavior id="id124041" class="DisplayTextBehavior" enabled="true"><attributes><text id="name">Display Text</text><text id="bundleName">DisplayText.behavior</text><text id="text"><expression><reference keypath="game.attributes.id163695"/></expression></text><text id="font">American Typewriter</text><real id="size">64</real><index id="alignment">1</index><boolean id="wrap">false</boolean><color id="color"><real id="red">1</real><real id="green">1</real><real id="blue">1</real><real id="alpha">1</real></color><real id="offsetx">0</real><real id="offsety">0</real><index id="space">0</index><index id="directionSpace">0</index><angle id="direction">0</angle></attributes></behavior></behaviors></actor><actor id="id204444" prototype="id445123"><attributes><text id="name">EnemyAttack</text><point id="position"><real id="x">159.13671875</real><real id="y">906.26171875</real></point></attributes><aspects/><behaviors><behavior id="id124041" class="DisplayTextBehavior" enabled="true"><attributes><text name="Name" id="name">Display Text</text><text name="Bundle Name" id="bundleName">DisplayText.behavior</text><text name="Text" id="text"><expression><reference keypath="game.attributes.id646870"/></expression></text><text name="Font" id="font">American Typewriter</text><real name="Size" id="size">64</real><index name="Alignment" id="alignment">1</index><boolean name="Wrap" id="wrap">false</boolean><color id="color"><real name="Red" id="red">1</real><real name="Green" id="green">1</real><real name="Blue" id="blue">1</real><real name="Alpha" id="alpha">1</real></color><real name="Offsetx" id="offsetx">0</real><real name="Offsety" id="offsety">0</real><index name="Space" id="space">0</index><index name="Direction Space" id="directionSpace">0</index><angle name="Direction" id="direction">0</angle></attributes></behavior></behaviors></actor></actors><attributes><text id="name">Background</text><boolean id="scrollable">true</boolean></attributes></layer></layers><attributes><text id="name">Main Game</text><real id="time">0</real><size id="size"><real id="width">768</real><real id="height">1024</real></size><boolean id="wrapX">false</boolean><boolean id="wrapY">false</boolean><point id="gravity"><real id="x">0</real><real id="y">0</real></point><color id="color"><real id="red">0</real><real id="green">0</real><real id="blue">0</real><real id="alpha">1</real></color><rect id="camera"><point id="origin"><real id="x">0</real><real id="y">0</real></point><size id="size"><real id="width">768</real><real id="height">1024</real></size><size id="trackingArea"><real id="width">688</real><real id="height">944</real></size><real id="rotation">0</real></rect><attributes id="autorotate"><boolean id="landscapeLeft">false</boolean><boolean id="portrait">true</boolean><boolean id="landscapeRight">false</boolean><boolean id="portraitUpsideDown">false</boolean></attributes></attributes></scene>
